radcompressor/__init__.py
radcompressor/compressor.py
radcompressor/condition.py
radcompressor/correlations.py
radcompressor/diffuser.py
radcompressor/geometry.py
radcompressor/impeller.py
radcompressor/inducer.py
radcompressor/plotting.py
radcompressor/thermo.py
radcompressor/utils.py
radcompressor/thermolibs/__init__.py
radcompressor/thermolibs/base.py
radcompressor/thermolibs/coolprop.py
radcompressor/thermolibs/refprop.py
radcompressor-1.0.1.dist-info/licenses/LICENSE
radcompressor-1.0.1.dist-info/METADATA
radcompressor-1.0.1.dist-info/WHEEL
radcompressor-1.0.1.dist-info/top_level.txt
radcompressor-1.0.1.dist-info/RECORD
