Metadata-Version: 2.4
Name: radcompressor
Version: 1.0.1
Summary: A mean-line analysis model for radial compressors
Author-email: Cyril Picard <cyrilp@mit.edu>
License: MIT License
Project-URL: Homepage, https://github.com/cyrilpic/radcomp
Project-URL: Repository, https://github.com/cyrilpic/radcomp.git
Requires-Python: >=3.8
License-File: LICENSE
Requires-Dist: numpy
Requires-Dist: scipy
Requires-Dist: CoolProp>=6.4.3
Provides-Extra: generate
Requires-Dist: click>=8.0.0; extra == "generate"
Requires-Dist: dask>=2.0.0; extra == "generate"
Requires-Dist: dask_mpi; extra == "generate"
Requires-Dist: pandas>=1.4.0; extra == "generate"
Requires-Dist: pyarrow>=11.0.0; extra == "generate"
Provides-Extra: test
Requires-Dist: pytest>=6.0.0; extra == "test"
Dynamic: license-file
